{
  "data": {
    "assists": [
      [
        150816,
        null,
        1,
        0
      ],
      [
        154322,
        "SECRET",
        1,
        0
      ],
      [
        210441,
        "SECRET",
        1,
        0
      ],
      [
        223468,
        null,
        1,
        0
      ],
      [
        358740,
        "SECRET",
        1,
        0
      ],
      [
        538609,
        null,
        1,
        0
      ],
      [
        582696,
        null,
        1,
        0
      ],
      [
        590712,
        "GLIU",
        1,
        0
      ],
      [
        597725,
        "SECRET",
        1,
        0
      ],
      [
        798648,
        null,
        0,
        1
      ],
      [
        811175,
        "SECRET",
        1,
        0
      ],
      [
        904873,
        null,
        0,
        1
      ],
      [
        992047,
        null,
        0,
        1
      ],
      [
        992548,
        "GLIU",
        1,
        0
      ]
    ],
    "deaths": 10,
    "end_sr": 2595,
    "game_duration": 1194,
    "game_ended": 1496750315,
    "game_started": 1496749077,
    "hero_statistics": {
      "ALL": {
        "damage": 11481,
        "deaths": 10,
        "elims": 17,
        "healing": 6950,
        "hero_stat_1": 11,
        "hero_stat_2": 3,
        "hero_stat_3": 11,
        "hero_stat_5": 17,
        "hero_stat_6": 1194472,
        "objective_kills": 9,
        "objective_time": 98,
        "tab_health": 0.6153846153846154,
        "time_played": 1114297
      },
      "junkrat": {
        "damage": 5694,
        "deaths": 2,
        "elims": 6,
        "healing": 0,
        "hero_stat_1": 27,
        "hero_stat_2": 2,
        "hero_stat_3": 6,
        "hero_stat_4": 1,
        "hero_stat_5": 4,
        "objective_kills": 5,
        "objective_time": 23,
        "tab_health": 0.6153846153846154,
        "time_played": 181374
      },
      "mei": {
        "damage": 1538,
        "deaths": 2,
        "elims": 2,
        "healing": 255,
        "hero_stat_1": 1141,
        "hero_stat_2": 0,
        "hero_stat_3": 2,
        "hero_stat_4": 255,
        "hero_stat_5": 3,
        "objective_kills": 1,
        "objective_time": 12,
        "tab_health": 0.6153846153846154,
        "time_played": 119742
      },
      "mercy": {
        "damage": 576,
        "deaths": 3,
        "elims": 2,
        "healing": 6695,
        "hero_stat_1": 10,
        "hero_stat_2": 2,
        "hero_stat_3": 17,
        "hero_stat_4": 755,
        "hero_stat_5": 4,
        "objective_kills": 2,
        "objective_time": 59,
        "tab_health": 0.6153846153846154,
        "time_played": 474478
      },
      "symmetra": {
        "damage": 1867,
        "deaths": 1,
        "elims": 2,
        "healing": 0,
        "hero_stat_1": 2,
        "hero_stat_2": 1,
        "hero_stat_3": 2,
        "hero_stat_4": 22,
        "hero_stat_5": 201,
        "objective_kills": 0,
        "objective_time": 0,
        "tab_health": 0.6153846153846154,
        "time_played": 143799
      },
      "widowmaker": {
        "damage": 1806,
        "deaths": 2,
        "elims": 5,
        "healing": 0,
        "hero_stat_1": 0,
        "hero_stat_2": 65,
        "hero_stat_3": 3,
        "hero_stat_4": 2,
        "hero_stat_5": 2,
        "objective_kills": 1,
        "objective_time": 15,
        "tab_health": 0.6153846153846154,
        "time_played": 118239
      }
    },
    "key": "notrob-1514/2017-06-06-11-58-9Jj9J3jXbznAhrBaPH36nH",
    "killfeed": [
      [
        141297,
        0,
        "pharah",
        "@UNKNOWN_RED#2",
        "reinhardt",
        "CR4ZYMALUCO",
        [
        ]
      ],
      [
        149313,
        0,
        "reinhardt",
        "MERCYNOMERCY",
        "roadhog",
        "BLOOMINATI",
        [
        ]
      ],
      [
        150816,
        1,
        null,
        null,
        "reinhardt",
        "MERCYNOMERCY",
        [
        ]
      ],
      [
        151317,
        1,
        "lucio",
        "ELIUSIVE",
        "reinhardt",
        "MERCYNOMERCY",
        [
        ]
      ],
      [
        154322,
        1,
        "s76",
        "ERNAHRUNG",
        "winston",
        "SECRET",
        [
        ]
      ],
      [
        155324,
        2,
        "mercy",
        "@UNKNOWN_RED#1",
        "winston",
        "SECRET",
        [
        ]
      ],
      [
        155324,
        2,
        "mercy",
        "@UNKNOWN_RED#1",
        "reinhardt",
        "MERCYNOMERCY",
        [
        ]
      ],
      [
        171858,
        0,
        "winston",
        "SECRET",
        "symmetra",
        "NOTROB",
        [
        ]
      ],
      [
        174363,
        0,
        "reinhardt",
        "MERCYNOMERCY",
        "mercy",
        "KEYINE",
        [
        ]
      ],
      [
        175364,
        1,
        "reinhardt",
        "CR4ZYMALUCO",
        "reinhardt",
        "MERCYNOMERCY",
        [
        ]
      ],
      [
        179374,
        1,
        "reinhardt",
        "CR4ZYMALUCO",
        "zarya",
        "GLIU",
        [
        ]
      ],
      [
        180876,
        1,
        "lucio",
        "ELIUSIVE",
        "winston",
        "SECRET",
        [
        ]
      ],
      [
        182881,
        0,
        "pharah",
        "@UNKNOWN_RED#2",
        "symmetra_teleporter",
        "NOTROB",
        [
        ]
      ],
      [
        184385,
        1,
        null,
        null,
        "pharah",
        "@UNKNOWN_RED#2",
        [
        ]
      ],
      [
        194909,
        1,
        "s76",
        "ERNAHRUNG",
        "mercy",
        "@UNKNOWN_RED#1",
        [
        ]
      ],
      [
        209940,
        1,
        "lucio",
        "ELIUSIVE",
        "winston",
        "SECRET",
        [
        ]
      ],
      [
        223468,
        1,
        "mei",
        "NOTROB",
        "reinhardt",
        "MERCYNOMERCY",
        [
        ]
      ],
      [
        230482,
        0,
        "winston",
        "SECRET",
        "roadhog",
        "BLOOMINATI",
        [
        ]
      ],
      [
        231484,
        1,
        null,
        null,
        "reinhardt",
        "MERCYNOMERCY",
        [
        ]
      ],
      [
        232485,
        2,
        "mercy",
        "@UNKNOWN_RED#1",
        "reinhardt",
        "MERCYNOMERCY",
        [
        ]
      ],
      [
        238997,
        0,
        "genji",
        "@UNKNOWN_RED#0",
        "reinhardt",
        "CR4ZYMALUCO",
        [
        ]
      ],
      [
        240000,
        0,
        "pharah",
        "@UNKNOWN_RED#2",
        "lucio",
        "ELIUSIVE",
        [
        ]
      ],
      [
        244510,
        3,
        "mercy",
        "KEYINE",
        "reinhardt",
        "CR4ZYMALUCO",
        [
        ]
      ],
      [
        245011,
        3,
        "mercy",
        "KEYINE",
        "lucio",
        "ELIUSIVE",
        [
        ]
      ],
      [
        245512,
        1,
        "s76",
        "ERNAHRUNG",
        "genji",
        "@UNKNOWN_RED#0",
        [
        ]
      ],
      [
        247516,
        0,
        "pharah",
        "@UNKNOWN_RED#2",
        "mei",
        "NOTROB",
        [
          "mercy"
        ]
      ],
      [
        252525,
        0,
        "winston",
        "SECRET",
        "reinhardt",
        "CR4ZYMALUCO",
        [
          "zarya"
        ]
      ],
      [
        255030,
        0,
        "pharah",
        "@UNKNOWN_RED#2",
        "lucio",
        "ELIUSIVE",
        [
          "mercy"
        ]
      ],
      [
        256534,
        0,
        "mercy",
        "@UNKNOWN_RED#1",
        "s76",
        "ERNAHRUNG",
        [
        ]
      ],
      [
        258538,
        0,
        "zarya",
        "GLIU",
        "mercy",
        "KEYINE",
        [
        ]
      ],
      [
        267556,
        0,
        "pharah",
        "@UNKNOWN_RED#2",
        "roadhog",
        "BLOOMINATI",
        [
        ]
      ],
      [
        303125,
        1,
        "roadhog",
        "BLOOMINATI",
        "mercy",
        "@UNKNOWN_RED#1",
        [
          "mercy"
        ]
      ],
      [
        303626,
        0,
        "genji",
        "@UNKNOWN_RED#0",
        "mei",
        "NOTROB",
        [
        ]
      ],
      [
        309137,
        0,
        "pharah",
        "@UNKNOWN_RED#2",
        "reinhardt",
        "CR4ZYMALUCO",
        [
        ]
      ],
      [
        312144,
        1,
        "lucio",
        "ELIUSIVE",
        "reinhardt",
        "MERCYNOMERCY",
        [
          "mei"
        ]
      ],
      [
        315152,
        1,
        "roadhog",
        "BLOOMINATI",
        "winston",
        "SECRET",
        [
          "mei"
        ]
      ],
      [
        325673,
        1,
        "s76",
        "ERNAHRUNG",
        "pharah",
        "@UNKNOWN_RED#2",
        [
        ]
      ],
      [
        328179,
        2,
        "mercy",
        "@UNKNOWN_RED#1",
        "pharah",
        "@UNKNOWN_RED#2",
        [
        ]
      ],
      [
        330183,
        1,
        null,
        null,
        "pharah",
        "@UNKNOWN_RED#2",
        [
        ]
      ],
      [
        334693,
        1,
        "widowmaker",
        "NOTROB",
        "pharah",
        "@UNKNOWN_RED#2",
        [
        ]
      ],
      [
        336195,
        0,
        "winston",
        "SECRET",
        "lucio",
        "ELIUSIVE",
        [
        ]
      ],
      [
        345213,
        0,
        "reinhardt",
        "MERCYNOMERCY",
        "roadhog",
        "BLOOMINATI",
        [
        ]
      ],
      [
        350222,
        1,
        "widowmaker",
        "NOTROB",
        "mercy",
        "@UNKNOWN_RED#1",
        [
        ]
      ],
      [
        353227,
        1,
        "s76",
        "ERNAHRUNG",
        "reinhardt",
        "MERCYNOMERCY",
        [
          "mercy",
          "reinhardt"
        ]
      ],
      [
        357237,
        0,
        "winston",
        "SECRET",
        "s76",
        "ERNAHRUNG",
        [
        ]
      ],
      [
        358740,
        1,
        "reinhardt",
        "CR4ZYMALUCO",
        "winston",
        "SECRET",
        [
        ]
      ],
      [
        361243,
        0,
        null,
        null,
        "lucio",
        "ELIUSIVE",
        [
        ]
      ],
      [
        368257,
        0,
        "genji",
        "@UNKNOWN_RED#0",
        "mercy",
        "KEYINE",
        [
        ]
      ],
      [
        370262,
        0,
        "pharah",
        "@UNKNOWN_RED#2",
        "reinhardt",
        "CR4ZYMALUCO",
        [
        ]
      ],
      [
        372267,
        0,
        null,
        null,
        "roadhog",
        "BLOOMINATI",
        [
        ]
      ],
      [
        374270,
        0,
        "genji",
        "@UNKNOWN_RED#0",
        "widowmaker",
        "NOTROB",
        [
        ]
      ],
      [
        384291,
        0,
        "genji",
        "@UNKNOWN_RED#0",
        "lucio",
        "ELIUSIVE",
        [
          "mercy"
        ]
      ],
      [
        428379,
        1,
        "roadhog",
        "BLOOMINATI",
        "reinhardt",
        "MERCYNOMERCY",
        [
          "mercy"
        ]
      ],
      [
        429882,
        0,
        "winston",
        "SECRET",
        "widowmaker",
        "NOTROB",
        [
        ]
      ],
      [
        434392,
        0,
        "genji",
        "@UNKNOWN_RED#0",
        "lucio",
        "ELIUSIVE",
        [
        ]
      ],
      [
        434392,
        2,
        "mercy",
        "@UNKNOWN_RED#1",
        "reinhardt",
        "MERCYNOMERCY",
        [
        ]
      ],
      [
        435896,
        1,
        "roadhog",
        "BLOOMINATI",
        "pharah",
        "@UNKNOWN_RED#2",
        [
        ]
      ],
      [
        437398,
        1,
        null,
        null,
        "reinhardt",
        "MERCYNOMERCY",
        [
        ]
      ],
      [
        437899,
        0,
        "winston",
        "SECRET",
        "mercy",
        "KEYINE",
        [
        ]
      ],
      [
        442910,
        0,
        "winston",
        "SECRET",
        "s76",
        "ERNAHRUNG",
        [
        ]
      ],
      [
        448422,
        0,
        "reinhardt",
        "MERCYNOMERCY",
        "dva_mech",
        "CR4ZYMALUCO",
        [
          "mercy"
        ]
      ],
      [
        449927,
        0,
        "reinhardt",
        "MERCYNOMERCY",
        "roadhog",
        "BLOOMINATI",
        [
        ]
      ],
      [
        454436,
        0,
        "winston",
        "SECRET",
        "lucio",
        "ELIUSIVE",
        [
        ]
      ],
      [
        455940,
        0,
        "reinhardt",
        "MERCYNOMERCY",
        "dva",
        "CR4ZYMALUCO",
        [
        ]
      ],
      [
        457944,
        3,
        "mercy",
        "KEYINE",
        "roadhog",
        "BLOOMINATI",
        [
        ]
      ],
      [
        457944,
        3,
        "mercy",
        "KEYINE",
        "lucio",
        "ELIUSIVE",
        [
        ]
      ],
      [
        457944,
        3,
        "mercy",
        "KEYINE",
        "dva",
        "CR4ZYMALUCO",
        [
        ]
      ],
      [
        458945,
        0,
        "zarya",
        "GLIU",
        "junkrat",
        "NOTROB",
        [
        ]
      ],
      [
        461450,
        1,
        "s76",
        "ERNAHRUNG",
        "mercy",
        "@UNKNOWN_RED#1",
        [
        ]
      ],
      [
        467461,
        1,
        "dva",
        "CR4ZYMALUCO",
        "genji",
        "@UNKNOWN_RED#0",
        [
          "roadhog"
        ]
      ],
      [
        467962,
        1,
        "dva",
        "CR4ZYMALUCO",
        "reinhardt",
        "MERCYNOMERCY",
        [
        ]
      ],
      [
        470467,
        0,
        "winston",
        "SECRET",
        "mercy",
        "KEYINE",
        [
        ]
      ],
      [
        470969,
        1,
        "roadhog",
        "BLOOMINATI",
        "winston",
        "SECRET",
        [
        ]
      ],
      [
        471971,
        1,
        "s76",
        "ERNAHRUNG",
        "zarya",
        "GLIU",
        [
        ]
      ],
      [
        472472,
        0,
        "zarya",
        "GLIU",
        "dva_mech",
        "CR4ZYMALUCO",
        [
        ]
      ],
      [
        487005,
        0,
        null,
        null,
        "dva",
        "CR4ZYMALUCO",
        [
        ]
      ],
      [
        508045,
        0,
        "genji",
        "@UNKNOWN_RED#0",
        "mercy",
        "KEYINE",
        [
        ]
      ],
      [
        509548,
        1,
        "dva",
        "CR4ZYMALUCO",
        "genji",
        "@UNKNOWN_RED#0",
        [
        ]
      ],
      [
        509548,
        1,
        "dva",
        "CR4ZYMALUCO",
        "zarya",
        "GLIU",
        [
        ]
      ],
      [
        517064,
        2,
        "mercy",
        "@UNKNOWN_RED#1",
        "zarya",
        "GLIU",
        [
        ]
      ],
      [
        517064,
        2,
        "mercy",
        "@UNKNOWN_RED#1",
        "genji",
        "@UNKNOWN_RED#0",
        [
        ]
      ],
      [
        519568,
        1,
        "s76",
        "ERNAHRUNG",
        "pharah",
        "@UNKNOWN_RED#2",
        [
        ]
      ],
      [
        519568,
        0,
        "reinhardt",
        "MERCYNOMERCY",
        "dva_mech",
        "CR4ZYMALUCO",
        [
        ]
      ],
      [
        531093,
        1,
        "s76",
        "ERNAHRUNG",
        "winston",
        "SECRET",
        [
        ]
      ],
      [
        532095,
        1,
        "s76",
        "ERNAHRUNG",
        "mercy",
        "@UNKNOWN_RED#1",
        [
        ]
      ],
      [
        533598,
        0,
        "genji",
        "@UNKNOWN_RED#0",
        "dva",
        "CR4ZYMALUCO",
        [
        ]
      ],
      [
        535603,
        0,
        "zarya",
        "GLIU",
        "lucio",
        "ELIUSIVE",
        [
        ]
      ],
      [
        538609,
        1,
        "junkrat",
        "NOTROB",
        "reinhardt",
        "MERCYNOMERCY",
        [
          "mercy"
        ]
      ],
      [
        547626,
        1,
        "roadhog",
        "BLOOMINATI",
        "genji",
        "@UNKNOWN_RED#0",
        [
        ]
      ],
      [
        559148,
        1,
        "roadhog",
        "BLOOMINATI",
        "winston",
        "SECRET",
        [
        ]
      ],
      [
        582696,
        1,
        "junkrat",
        "NOTROB",
        "reinhardt",
        "MERCYNOMERCY",
        [
        ]
      ],
      [
        590712,
        1,
        "junkrat",
        "NOTROB",
        "zarya",
        "GLIU",
        [
        ]
      ],
      [
        594720,
        2,
        "mercy",
        "@UNKNOWN_RED#1",
        "reinhardt",
        "MERCYNOMERCY",
        [
        ]
      ],
      [
        594720,
        2,
        "mercy",
        "@UNKNOWN_RED#1",
        "zarya",
        "GLIU",
        [
        ]
      ],
      [
        597225,
        1,
        "roadhog",
        "BLOOMINATI",
        "reaper",
        "SECRET",
        [
        ]
      ],
      [
        597225,
        1,
        "winston",
        "CR4ZYMALUCO",
        "ana",
        "@UNKNOWN_RED#2",
        [
        ]
      ],
      [
        603737,
        1,
        "junkrat",
        "NOTROB",
        "mercy",
        "@UNKNOWN_RED#1",
        [
        ]
      ],
      [
        607246,
        1,
        "lucio",
        "ELIUSIVE",
        "reinhardt",
        "MERCYNOMERCY",
        [
          "roadhog"
        ]
      ],
      [
        612759,
        1,
        "winston",
        "CR4ZYMALUCO",
        "zarya",
        "GLIU",
        [
        ]
      ],
      [
        619274,
        1,
        "lucio",
        "ELIUSIVE",
        "genji",
        "@UNKNOWN_RED#0",
        [
        ]
      ],
      [
        757566,
        1,
        "roadhog",
        "BLOOMINATI",
        "mercy",
        "@UNKNOWN_RED#1",
        [
          "mercy"
        ]
      ],
      [
        765581,
        1,
        "winston",
        "ELIUSIVE",
        "reinhardt",
        "MERCYNOMERCY",
        [
          "ana",
          "mercy"
        ]
      ],
      [
        776099,
        1,
        "roadhog",
        "BLOOMINATI",
        "winston",
        "SECRET",
        [
        ]
      ],
      [
        783616,
        1,
        "winston",
        "ELIUSIVE",
        "ana",
        "@UNKNOWN_RED#2",
        [
          "mercy"
        ]
      ],
      [
        785119,
        0,
        "genji",
        "@UNKNOWN_RED#0",
        "ana",
        "KEYINE",
        [
          "ana"
        ]
      ],
      [
        791131,
        1,
        "pharah",
        "ERNAHRUNG",
        "genji",
        "@UNKNOWN_RED#0",
        [
        ]
      ],
      [
        795641,
        1,
        "winston",
        "ELIUSIVE",
        "s76",
        "GLIU",
        [
        ]
      ],
      [
        798648,
        1,
        "pharah",
        "ERNAHRUNG",
        "reinhardt",
        "MERCYNOMERCY",
        [
          "mercy",
          "roadhog"
        ]
      ],
      [
        805161,
        1,
        "winston",
        "ELIUSIVE",
        "mercy",
        "@UNKNOWN_RED#1",
        [
        ]
      ],
      [
        811175,
        1,
        "roadhog",
        "BLOOMINATI",
        "winston",
        "SECRET",
        [
        ]
      ],
      [
        814183,
        1,
        "roadhog",
        "BLOOMINATI",
        "ana",
        "@UNKNOWN_RED#2",
        [
        ]
      ],
      [
        816688,
        0,
        "genji",
        "@UNKNOWN_RED#0",
        "s76",
        "CR4ZYMALUCO",
        [
          "ana"
        ]
      ],
      [
        821198,
        0,
        "s76",
        "GLIU",
        "mercy",
        "NOTROB",
        [
        ]
      ],
      [
        834224,
        1,
        "roadhog",
        "BLOOMINATI",
        "reinhardt",
        "MERCYNOMERCY",
        [
          "ana"
        ]
      ],
      [
        835226,
        1,
        "roadhog",
        "BLOOMINATI",
        "mercy",
        "@UNKNOWN_RED#1",
        [
        ]
      ],
      [
        838232,
        0,
        "genji",
        "@UNKNOWN_RED#0",
        "ana",
        "KEYINE",
        [
        ]
      ],
      [
        839234,
        1,
        "winston",
        "ELIUSIVE",
        "s76",
        "GLIU",
        [
        ]
      ],
      [
        840738,
        1,
        "s76",
        "CR4ZYMALUCO",
        "genji",
        "@UNKNOWN_RED#0",
        [
        ]
      ],
      [
        842742,
        0,
        "ana",
        "@UNKNOWN_RED#2",
        "pharah",
        "ERNAHRUNG",
        [
        ]
      ],
      [
        844745,
        0,
        "winston",
        "SECRET",
        "roadhog",
        "BLOOMINATI",
        [
        ]
      ],
      [
        852761,
        1,
        "winston",
        "ELIUSIVE",
        "ana",
        "@UNKNOWN_RED#2",
        [
        ]
      ],
      [
        855267,
        0,
        "winston",
        "SECRET",
        "s76",
        "CR4ZYMALUCO",
        [
          "ana"
        ]
      ],
      [
        864789,
        0,
        "reinhardt",
        "MERCYNOMERCY",
        "winston",
        "ELIUSIVE",
        [
        ]
      ],
      [
        896854,
        1,
        "pharah",
        "ERNAHRUNG",
        "mercy",
        "@UNKNOWN_RED#1",
        [
          "mercy"
        ]
      ],
      [
        897355,
        0,
        "genji",
        "@UNKNOWN_RED#0",
        "winston",
        "ELIUSIVE",
        [
        ]
      ],
      [
        898357,
        1,
        "s76",
        "CR4ZYMALUCO",
        "ana",
        "@UNKNOWN_RED#2",
        [
          "mercy",
          "ana"
        ]
      ],
      [
        898357,
        1,
        "roadhog",
        "BLOOMINATI",
        "s76",
        "GLIU",
        [
          "ana"
        ]
      ],
      [
        898857,
        0,
        "genji",
        "@UNKNOWN_RED#0",
        "pharah",
        "ERNAHRUNG",
        [
        ]
      ],
      [
        899860,
        3,
        "mercy",
        "NOTROB",
        "pharah",
        "ERNAHRUNG",
        [
        ]
      ],
      [
        899860,
        3,
        "mercy",
        "NOTROB",
        "winston",
        "ELIUSIVE",
        [
        ]
      ],
      [
        903369,
        1,
        "roadhog",
        "BLOOMINATI",
        "genji",
        "@UNKNOWN_RED#0",
        [
        ]
      ],
      [
        904873,
        1,
        "s76",
        "CR4ZYMALUCO",
        "reinhardt",
        "MERCYNOMERCY",
        [
          "ana",
          "mercy"
        ]
      ],
      [
        908378,
        1,
        "roadhog",
        "BLOOMINATI",
        "winston",
        "SECRET",
        [
          "mercy",
          "ana"
        ]
      ],
      [
        924914,
        1,
        "roadhog",
        "BLOOMINATI",
        "s76",
        "GLIU",
        [
        ]
      ],
      [
        954475,
        0,
        null,
        null,
        "roadhog",
        "BLOOMINATI",
        [
        ]
      ],
      [
        966498,
        1,
        "s76",
        "CR4ZYMALUCO",
        "winston",
        "SECRET",
        [
          "mercy"
        ]
      ],
      [
        972008,
        0,
        "s76",
        "GLIU",
        "pharah",
        "ERNAHRUNG",
        [
        ]
      ],
      [
        974011,
        1,
        "winston",
        "ELIUSIVE",
        "genji",
        "@UNKNOWN_RED#0",
        [
          "mercy"
        ]
      ],
      [
        980527,
        1,
        "s76",
        "CR4ZYMALUCO",
        "mercy",
        "@UNKNOWN_RED#1",
        [
          "roadhog",
          "ana"
        ]
      ],
      [
        990544,
        0,
        "s76",
        "GLIU",
        "ana",
        "KEYINE",
        [
        ]
      ],
      [
        991044,
        0,
        "s76",
        "GLIU",
        "s76",
        "CR4ZYMALUCO",
        [
        ]
      ],
      [
        992047,
        1,
        "roadhog",
        "BLOOMINATI",
        "reinhardt",
        "MERCYNOMERCY",
        [
        ]
      ],
      [
        993049,
        1,
        "winston",
        "ELIUSIVE",
        "s76",
        "GLIU",
        [
        ]
      ],
      [
        1002068,
        1,
        "pharah",
        "ERNAHRUNG",
        "winston",
        "SECRET",
        [
          "roadhog"
        ]
      ],
      [
        1015598,
        0,
        "s76",
        "GLIU",
        "pharah",
        "ERNAHRUNG",
        [
        ]
      ],
      [
        1024116,
        0,
        "genji",
        "@UNKNOWN_RED#0",
        "mercy",
        "NOTROB",
        [
        ]
      ],
      [
        1025618,
        0,
        "genji",
        "@UNKNOWN_RED#0",
        "s76",
        "CR4ZYMALUCO",
        [
          "reinhardt"
        ]
      ],
      [
        1025618,
        0,
        "winston",
        "SECRET",
        "winston",
        "ELIUSIVE",
        [
          "reinhardt"
        ]
      ],
      [
        1026620,
        0,
        "genji",
        "@UNKNOWN_RED#0",
        "roadhog",
        "BLOOMINATI",
        [
        ]
      ],
      [
        1030627,
        0,
        "winston",
        "SECRET",
        "ana",
        "KEYINE",
        [
          "ana"
        ]
      ],
      [
        1074719,
        0,
        "s76",
        "GLIU",
        "winston",
        "ELIUSIVE",
        [
        ]
      ],
      [
        1076724,
        0,
        "s76",
        "GLIU",
        "s76",
        "CR4ZYMALUCO",
        [
          "ana",
          "mercy"
        ]
      ],
      [
        1077226,
        3,
        "mercy",
        "NOTROB",
        "s76",
        "CR4ZYMALUCO",
        [
        ]
      ],
      [
        1077226,
        3,
        "mercy",
        "NOTROB",
        "winston",
        "ELIUSIVE",
        [
        ]
      ],
      [
        1081735,
        0,
        "genji",
        "@UNKNOWN_RED#0",
        "s76",
        "CR4ZYMALUCO",
        [
          "ana"
        ]
      ],
      [
        1089752,
        0,
        "s76",
        "GLIU",
        "winston",
        "ELIUSIVE",
        [
          "ana"
        ]
      ],
      [
        1091255,
        1,
        "roadhog",
        "BLOOMINATI",
        "s76",
        "GLIU",
        [
        ]
      ],
      [
        1092258,
        0,
        "genji",
        "@UNKNOWN_RED#0",
        "roadhog",
        "BLOOMINATI",
        [
        ]
      ],
      [
        1096265,
        2,
        "mercy",
        "@UNKNOWN_RED#1",
        "s76",
        "GLIU",
        [
        ]
      ],
      [
        1096766,
        1,
        null,
        null,
        "s76",
        "GLIU",
        [
        ]
      ],
      [
        1105785,
        0,
        "s76",
        "GLIU",
        "mercy",
        "NOTROB",
        [
        ]
      ],
      [
        1116806,
        1,
        "mccree",
        "CR4ZYMALUCO",
        "winston",
        "SECRET",
        [
          "ana"
        ]
      ],
      [
        1127828,
        0,
        "reinhardt",
        "MERCYNOMERCY",
        "winston",
        "ELIUSIVE",
        [
          "ana"
        ]
      ],
      [
        1128831,
        1,
        "mccree",
        "CR4ZYMALUCO",
        "s76",
        "GLIU",
        [
        ]
      ],
      [
        1132839,
        0,
        "genji",
        "@UNKNOWN_RED#0",
        "mccree",
        "CR4ZYMALUCO",
        [
        ]
      ],
      [
        1140353,
        0,
        "winston",
        "SECRET",
        "ana",
        "KEYINE",
        [
          "reinhardt",
          "ana"
        ]
      ],
      [
        1142358,
        0,
        "mercy",
        "@UNKNOWN_RED#1",
        "roadhog",
        "BLOOMINATI",
        [
          "reinhardt"
        ]
      ],
      [
        1152380,
        1,
        "pharah",
        "ERNAHRUNG",
        "reinhardt",
        "MERCYNOMERCY",
        [
        ]
      ],
      [
        1156387,
        0,
        "s76",
        "GLIU",
        "mercy",
        "NOTROB",
        [
        ]
      ],
      [
        1167913,
        0,
        null,
        null,
        "pharah",
        "ERNAHRUNG",
        [
        ]
      ]
    ],
    "map": "Eichenwalde",
    "map_type": "Hybrid",
    "objective_stages": [
      {
        "checkpoints": [
          [
            268557,
            1
          ],
          [
            393310,
            2
          ]
        ],
        "end": 627792,
        "end_score": 2,
        "stage": "Defend",
        "start": 40084
      },
      {
        "checkpoints": [
          [
            912888,
            1
          ]
        ],
        "end": 1159393,
        "end_score": 1,
        "stage": "Attack",
        "start": 638314
      }
    ],
    "owner": "notrob#1514",
    "player": "NOTROB",
    "result": "LOSS",
    "score": [
      1,
      2
    ],
    "start_sr": 2615,
    "tab_statistics": {
      "damage": [
        0,
        0,
        0,
        0,
        1867,
        1867,
        1867,
        1867,
        1867,
        2682,
        2682,
        2682,
        2682,
        2682,
        3246,
        3405,
        null,
        3405,
        4429,
        4429,
        4429,
        5211,
        5211,
        5211,
        6458,
        6458,
        6458,
        8145,
        8225,
        10634,
        10905,
        10905,
        10905,
        10905,
        10905,
        10905,
        10905,
        10905,
        10965,
        10965,
        10965,
        10965,
        10965,
        11080,
        11080,
        11180,
        11270,
        11270,
        11270,
        11270,
        11481,
        11481,
        11481,
        11481,
        11481
      ],
      "deaths": [
        0,
        0,
        0,
        0,
        1,
        1,
        1,
        1,
        1,
        2,
        2,
        2,
        2,
        2,
        3,
        3,
        null,
        3,
        4,
        4,
        4,
        5,
        5,
        5,
        6,
        6,
        6,
        7,
        7,
        7,
        7,
        7,
        7,
        7,
        7,
        7,
        7,
        7,
        8,
        8,
        8,
        8,
        8,
        8,
        8,
        8,
        9,
        9,
        9,
        9,
        10,
        10,
        10,
        10,
        10
      ],
      "elims": [
        0,
        0,
        0,
        0,
        2,
        2,
        2,
        2,
        2,
        4,
        4,
        4,
        4,
        4,
        4,
        4,
        null,
        6,
        9,
        9,
        9,
        9,
        9,
        9,
        9,
        9,
        9,
        9,
        9,
        13,
        15,
        15,
        15,
        15,
        15,
        15,
        15,
        15,
        16,
        16,
        16,
        16,
        16,
        16,
        16,
        16,
        17,
        17,
        17,
        17,
        17,
        17,
        17,
        17,
        17
      ],
      "healing": [
        0,
        0,
        0,
        0,
        0,
        0,
        0,
        0,
        0,
        169,
        169,
        169,
        169,
        169,
        255,
        255,
        null,
        255,
        255,
        255,
        255,
        255,
        255,
        255,
        255,
        255,
        255,
        255,
        255,
        255,
        255,
        255,
        255,
        255,
        255,
        255,
        255,
        565,
        2525,
        2525,
        2525,
        2525,
        2525,
        3640,
        3640,
        4159,
        5529,
        5529,
        5529,
        5529,
        6368,
        6368,
        6368,
        6368,
        6950
      ],
      "hero": [
        "symmetra",
        "symmetra",
        "symmetra",
        "symmetra",
        "symmetra",
        "symmetra",
        "symmetra",
        "mei",
        "mei",
        "mei",
        "mei",
        "mei",
        "mei",
        "mei",
        "mei",
        "mei",
        "widowmaker",
        "widowmaker",
        "widowmaker",
        "widowmaker",
        "widowmaker",
        "widowmaker",
        "widowmaker",
        "junkrat",
        "junkrat",
        "junkrat",
        "junkrat",
        "junkrat",
        "junkrat",
        "junkrat",
        "junkrat",
        "mercy",
        "mercy",
        "mercy",
        "mercy",
        "mercy",
        "mercy",
        "mercy",
        "mercy",
        "mercy",
        "mercy",
        "mercy",
        "mercy",
        "mercy",
        "mercy",
        "mercy",
        "mercy",
        "mercy",
        "mercy",
        "mercy",
        "mercy",
        "mercy",
        "mercy",
        "mercy",
        "mercy"
      ],
      "hero_stat_1": [
        0,
        0,
        0,
        0,
        2,
        2,
        2,
        0,
        0,
        917,
        1141,
        1141,
        1141,
        1141,
        1141,
        1141,
        null,
        0,
        0,
        0,
        0,
        0,
        0,
        0,
        43,
        43,
        38,
        44,
        44,
        33,
        27,
        0,
        0,
        0,
        0,
        0,
        0,
        0,
        4,
        4,
        4,
        4,
        4,
        8,
        8,
        9,
        10,
        10,
        10,
        10,
        10,
        10,
        10,
        10,
        10
      ],
      "hero_stat_2": [
        0,
        0,
        0,
        0,
        1,
        1,
        1,
        0,
        0,
        0,
        0,
        0,
        0,
        0,
        0,
        0,
        null,
        0,
        64,
        64,
        64,
        65,
        65,
        0,
        0,
        0,
        0,
        0,
        1,
        1,
        2,
        0,
        0,
        0,
        0,
        0,
        0,
        0,
        1,
        1,
        1,
        1,
        1,
        1,
        1,
        1,
        2,
        2,
        2,
        2,
        2,
        2,
        2,
        2,
        2
      ],
      "hero_stat_3": [
        0,
        0,
        0,
        0,
        2,
        2,
        2,
        0,
        0,
        2,
        2,
        2,
        2,
        2,
        2,
        2,
        null,
        0,
        3,
        3,
        3,
        3,
        3,
        0,
        0,
        0,
        0,
        0,
        0,
        4,
        6,
        0,
        0,
        0,
        0,
        0,
        0,
        0,
        9,
        9,
        9,
        9,
        9,
        12,
        12,
        13,
        17,
        17,
        17,
        17,
        17,
        17,
        17,
        17,
        17
      ],
      "hero_stat_4": [
        0,
        0,
        0,
        0,
        11,
        18,
        22,
        0,
        0,
        169,
        169,
        169,
        169,
        169,
        255,
        255,
        null,
        0,
        2,
        2,
        2,
        2,
        2,
        0,
        0,
        0,
        0,
        0,
        0,
        1,
        1,
        0,
        0,
        0,
        0,
        0,
        0,
        56,
        91,
        91,
        91,
        91,
        91,
        498,
        498,
        535,
        582,
        582,
        582,
        582,
        755,
        755,
        755,
        755,
        755
      ],
      "hero_stat_5": [
        0,
        0,
        0,
        0,
        201,
        201,
        201,
        0,
        0,
        1,
        1,
        1,
        1,
        1,
        1,
        3,
        null,
        0,
        2,
        2,
        2,
        2,
        2,
        0,
        0,
        0,
        0,
        0,
        0,
        3,
        4,
        0,
        0,
        0,
        0,
        0,
        0,
        0,
        0,
        0,
        0,
        0,
        0,
        2,
        2,
        2,
        2,
        2,
        2,
        2,
        4,
        4,
        4,
        4,
        4
      ],
      "hero_stat_6": [
        null,
        null,
        null,
        null,
        null,
        null,
        null,
        null,
        null,
        null,
        null,
        null,
        null,
        null,
        null,
        null,
        null,
        null,
        null,
        null,
        null,
        null,
        null,
        null,
        null,
        null,
        null,
        null,
        null,
        null,
        null,
        null,
        null,
        null,
        null,
        null,
        null,
        null,
        null,
        null,
        null,
        null,
        null,
        null,
        null,
        null,
        null,
        null,
        null,
        null,
        null,
        null,
        null,
        null,
        null
      ],
      "objective_kills": [
        0,
        0,
        0,
        0,
        0,
        0,
        0,
        0,
        0,
        1,
        1,
        1,
        1,
        1,
        1,
        1,
        1,
        1,
        2,
        2,
        2,
        2,
        2,
        2,
        2,
        2,
        2,
        2,
        2,
        6,
        7,
        7,
        7,
        7,
        7,
        7,
        7,
        7,
        8,
        8,
        8,
        8,
        8,
        8,
        8,
        8,
        9,
        9,
        9,
        9,
        9,
        9,
        9,
        9,
        9
      ],
      "objective_time": [
        0,
        0,
        0,
        0,
        0,
        0,
        0,
        0,
        0,
        12,
        12,
        12,
        12,
        12,
        12,
        12,
        1,
        12,
        16,
        16,
        16,
        16,
        16,
        16,
        16,
        16,
        16,
        16,
        16,
        23,
        39,
        39,
        39,
        39,
        39,
        39,
        39,
        39,
        49,
        49,
        49,
        49,
        49,
        55,
        60,
        67,
        87,
        87,
        87,
        87,
        92,
        92,
        92,
        92,
        98
      ],
      "time": [
        41087,
        46597,
        52107,
        58121,
        171356,
        177871,
        184886,
        190398,
        196913,
        248518,
        254028,
        259540,
        265052,
        275570,
        304628,
        310140,
        317657,
        323168,
        375272,
        381285,
        387798,
        430383,
        435896,
        440906,
        464956,
        469966,
        477484,
        520069,
        526080,
        591213,
        622280,
        680906,
        688422,
        716987,
        726004,
        731014,
        736023,
        755062,
        820697,
        825707,
        831219,
        836729,
        841740,
        918400,
        925415,
        968001,
        1025117,
        1030627,
        1035638,
        1041149,
        1106788,
        1112798,
        1118809,
        1124320,
        1155384
      ]
    },
    "teams": {
      "blue": [
        {
          "heroes": [
            {
              "end": 171858,
              "hero": "symmetra",
              "start": 171858
            },
            {
              "end": 303626,
              "hero": "mei",
              "start": 223468
            },
            {
              "end": 429882,
              "hero": "widowmaker",
              "start": 334693
            },
            {
              "end": 603737,
              "hero": "junkrat",
              "start": 458945
            },
            {
              "end": 1167913,
              "hero": "mercy",
              "start": 821198
            }
          ],
          "name": "NOTROB"
        },
        {
          "heroes": [
            {
              "end": 370262,
              "hero": "reinhardt",
              "start": 141297
            },
            {
              "end": 533598,
              "hero": "dva",
              "start": 455940
            },
            {
              "end": 612759,
              "hero": "winston",
              "start": 597225
            },
            {
              "end": 1081735,
              "hero": "s76",
              "start": 816688
            },
            {
              "end": 1167913,
              "hero": "mccree",
              "start": 1116806
            }
          ],
          "name": "CR4ZYMALUCO"
        },
        {
          "heroes": [
            {
              "end": 508045,
              "hero": "mercy",
              "start": 174363
            },
            {
              "end": 1167913,
              "hero": "ana",
              "start": 785119
            }
          ],
          "name": "KEYINE"
        },
        {
          "heroes": [
            {
              "end": 532095,
              "hero": "s76",
              "start": 154322
            },
            {
              "end": 1167913,
              "hero": "pharah",
              "start": 791131
            }
          ],
          "name": "ERNAHRUNG"
        },
        {
          "heroes": [
            {
              "end": 1167913,
              "hero": "roadhog",
              "start": 149313
            }
          ],
          "name": "BLOOMINATI"
        },
        {
          "heroes": [
            {
              "end": 619274,
              "hero": "lucio",
              "start": 151317
            },
            {
              "end": 1167913,
              "hero": "winston",
              "start": 765581
            }
          ],
          "name": "ELIUSIVE"
        }
      ],
      "red": [
        {
          "heroes": [
            {
              "end": 612759,
              "hero": "zarya",
              "start": 179374
            },
            {
              "end": 1167913,
              "hero": "s76",
              "start": 795641
            }
          ],
          "name": "GLIU"
        },
        {
          "heroes": [
            {
              "end": 559148,
              "hero": "winston",
              "start": 154322
            },
            {
              "end": 597225,
              "hero": "reaper",
              "start": 597225
            },
            {
              "end": 1167913,
              "hero": "winston",
              "start": 776099
            }
          ],
          "name": "SECRET"
        },
        {
          "heroes": [
            {
              "end": 1167913,
              "hero": "genji",
              "start": 238997
            }
          ],
          "name": "@UNKNOWN_RED#0"
        },
        {
          "heroes": [
            {
              "end": 1167913,
              "hero": "reinhardt",
              "start": 149313
            }
          ],
          "name": "MERCYNOMERCY"
        },
        {
          "heroes": [
            {
              "end": 1167913,
              "hero": "mercy",
              "start": 155324
            }
          ],
          "name": "@UNKNOWN_RED#1"
        },
        {
          "heroes": [
            {
              "end": 519568,
              "hero": "pharah",
              "start": 141297
            },
            {
              "end": 1167913,
              "hero": "ana",
              "start": 597225
            }
          ],
          "name": "@UNKNOWN_RED#2"
        }
      ]
    },
    "user_id": 2235147
  },
  "meta": {
    "duration": 1194,
    "end_sr": 2595,
    "heroes_played": [
      [
        "mercy",
        0.5199264006814085
      ],
      [
        "junkrat",
        0.21712698731656405
      ],
      [
        "widowmaker",
        0.14274338910766074
      ]
    ],
    "key": "notrob-1514/2017-06-06-11-58-9Jj9J3jXbznAhrBaPH36nH",
    "map": "Eichenwalde",
    "player_name": "NOTROB",
    "rank": null,
    "result": "LOSS",
    "score": [
      1,
      2
    ],
    "start_sr": 2615,
    "time": 1496749077,
    "url": "https://s3-us-west-2.amazonaws.com/overtrack-parsed-games/notrob-1514/2017-06-06-11-58-9Jj9J3jXbznAhrBaPH36nH/game.json",
    "user_id": 2235147
  }
}