{
  "data": {
    "assists": [
      [
        86175,
        "THESHADOWXIV",
        0,
        1
      ],
      [
        94694,
        "FROSTYFEET",
        1,
        0
      ],
      [
        98701,
        "SAVAGEWOLFIE",
        1,
        0
      ],
      [
        121753,
        "KONGLAZY",
        1,
        1
      ],
      [
        288106,
        "SAVAGEWOLFIE",
        1,
        0
      ],
      [
        454963,
        "SAVAGEWOLFIE",
        0,
        1
      ],
      [
        458469,
        "MINIMAL",
        1,
        1
      ],
      [
        463983,
        "THESHADOWXIV",
        1,
        1
      ],
      [
        472000,
        "FROSTYFEET",
        1,
        1
      ],
      [
        475507,
        "CUSZZ",
        1,
        1
      ],
      [
        489540,
        "THESHADOWXIV",
        0,
        1
      ],
      [
        568198,
        "MINIMAL",
        1,
        0
      ],
      [
        578221,
        "THESHADOWXIV",
        1,
        0
      ],
      [
        612292,
        "FROSTYFEET",
        0,
        1
      ],
      [
        619809,
        "SAVAGEWOLFIE",
        1,
        1
      ],
      [
        625820,
        "KONGLAZY",
        1,
        1
      ],
      [
        626822,
        "CUSZZ",
        1,
        1
      ],
      [
        669909,
        "MINIMAL",
        1,
        0
      ],
      [
        739060,
        "THESHADOWXIV",
        0,
        1
      ],
      [
        747579,
        "MINIMAL",
        0,
        1
      ],
      [
        764117,
        "THESHADOWXIV",
        0,
        1
      ],
      [
        838778,
        "THESHADOWXIV",
        0,
        1
      ],
      [
        849803,
        "KONGLAZY",
        0,
        1
      ],
      [
        913939,
        "THESHADOWXIV",
        0,
        1
      ],
      [
        914942,
        "SAVAGEWOLFIE",
        0,
        1
      ],
      [
        984594,
        "SAVAGEWOLFIE",
        0,
        1
      ],
      [
        992107,
        "FROSTYFEET",
        0,
        1
      ]
    ],
    "custom_game": false,
    "deaths": 13,
    "end_sr": 2605,
    "game_duration": 1018,
    "game_ended": 1497617421,
    "game_started": 1497616331,
    "hero_statistics": {
      "ALL": {
        "damage": 5179,
        "deaths": 13,
        "elims": 14,
        "healing": 10146,
        "hero_stat_1": 14,
        "hero_stat_2": 21,
        "hero_stat_3": 10,
        "hero_stat_5": 14,
        "hero_stat_6": 1018660,
        "objective_kills": 6,
        "objective_time": 106,
        "tab_health": 0.7058823529411765,
        "time_played": 976578
      },
      "lucio": {
        "damage": 2401,
        "deaths": 5,
        "elims": 4,
        "healing": 1990,
        "hero_stat_1": 26,
        "hero_stat_2": 2,
        "hero_stat_3": 3,
        "hero_stat_4": 2,
        "hero_stat_5": 5,
        "objective_kills": 1,
        "objective_time": 62,
        "tab_health": 0.7058823529411765,
        "time_played": 358763
      },
      "mercy": {
        "damage": 40,
        "deaths": 5,
        "elims": 0,
        "healing": 5664,
        "hero_stat_1": 3,
        "hero_stat_2": 0,
        "hero_stat_3": 9,
        "hero_stat_4": 104,
        "hero_stat_5": 4,
        "objective_kills": 0,
        "objective_time": 27,
        "tab_health": 0.7058823529411765,
        "time_played": 303653
      },
      "zenyatta": {
        "damage": 2738,
        "deaths": 3,
        "elims": 10,
        "healing": 2492,
        "hero_stat_1": 22,
        "hero_stat_2": 8,
        "hero_stat_3": 4,
        "hero_stat_4": 174,
        "hero_stat_5": 9,
        "objective_kills": 5,
        "objective_time": 17,
        "tab_health": 0.7058823529411765,
        "time_played": 293117
      }
    },
    "key": "notrob-1514/2017-06-16-12-50-kBYGWKWpbQqUmZUfjNWUXV",
    "killfeed": [
      [
        86175,
        1,
        "genji",
        "SENSOR",
        "winston",
        "THESHADOWXIV",
        [
          "ana"
        ]
      ],
      [
        94694,
        1,
        "winston",
        "BOOMBAT",
        "mercy",
        "FROSTYFEET",
        [
        ]
      ],
      [
        98701,
        1,
        "lucio",
        "NOTROB",
        "reaper",
        "SAVAGEWOLFIE",
        [
        ]
      ],
      [
        109726,
        1,
        "genji",
        "SENSOR",
        "genji",
        "MINIMAL",
        [
        ]
      ],
      [
        124259,
        0,
        "reaper",
        "SAVAGEWOLFIE",
        "lucio",
        "NOTROB",
        [
          "roadhog"
        ]
      ],
      [
        126263,
        1,
        "dva",
        "SOONO3O4",
        "winston",
        "THESHADOWXIV",
        [
        ]
      ],
      [
        128768,
        0,
        "reaper",
        "SAVAGEWOLFIE",
        "winston",
        "BOOMBAT",
        [
        ]
      ],
      [
        137286,
        0,
        "roadhog",
        "CUSZZ",
        "s76",
        "@UNKNOWN_BLUE#0",
        [
        ]
      ],
      [
        138288,
        1,
        "dva",
        "SOONO3O4",
        "roadhog",
        "CUSZZ",
        [
        ]
      ],
      [
        147309,
        2,
        "mercy",
        "FROSTYFEET",
        "roadhog",
        "CUSZZ",
        [
        ]
      ],
      [
        149313,
        1,
        null,
        null,
        "roadhog",
        "CUSZZ",
        [
        ]
      ],
      [
        149815,
        0,
        "reaper",
        "SAVAGEWOLFIE",
        "ana",
        "XXGROUPXXTH9",
        [
        ]
      ],
      [
        153822,
        0,
        "roadhog",
        "CUSZZ",
        "lucio",
        "NOTROB",
        [
        ]
      ],
      [
        155324,
        0,
        "roadhog",
        "CUSZZ",
        "genji",
        "SENSOR",
        [
        ]
      ],
      [
        155825,
        1,
        "winston",
        "BOOMBAT",
        "mercy",
        "FROSTYFEET",
        [
        ]
      ],
      [
        160835,
        0,
        "genji",
        "MINIMAL",
        "dva_mech",
        "SOONO3O4",
        [
        ]
      ],
      [
        160835,
        0,
        "genji",
        "MINIMAL",
        "dva",
        "SOONO3O4",
        [
        ]
      ],
      [
        170355,
        0,
        "genji",
        "MINIMAL",
        "winston",
        "BOOMBAT",
        [
          "roadhog"
        ]
      ],
      [
        200919,
        0,
        "reaper",
        "SAVAGEWOLFIE",
        "s76",
        "@UNKNOWN_BLUE#0",
        [
        ]
      ],
      [
        201921,
        0,
        "reaper",
        "SAVAGEWOLFIE",
        "ana",
        "XXGROUPXXTH9",
        [
        ]
      ],
      [
        209940,
        1,
        "winston",
        "BOOMBAT",
        "winston",
        "THESHADOWXIV",
        [
        ]
      ],
      [
        210943,
        0,
        "genji",
        "MINIMAL",
        "dva_mech",
        "SOONO3O4",
        [
          "mercy"
        ]
      ],
      [
        211946,
        1,
        "genji",
        "SENSOR",
        "genji",
        "MINIMAL",
        [
        ]
      ],
      [
        212447,
        0,
        "lucio",
        "KONGLAZY",
        "genji",
        "SENSOR",
        [
        ]
      ],
      [
        216455,
        0,
        "reaper",
        "SAVAGEWOLFIE",
        "winston",
        "BOOMBAT",
        [
          "mercy"
        ]
      ],
      [
        216455,
        0,
        "roadhog",
        "CUSZZ",
        "dva",
        "SOONO3O4",
        [
        ]
      ],
      [
        224974,
        0,
        "reaper",
        "SAVAGEWOLFIE",
        "lucio",
        "NOTROB",
        [
        ]
      ],
      [
        238501,
        0,
        null,
        null,
        "genji",
        "SENSOR",
        [
        ]
      ],
      [
        265057,
        0,
        "roadhog",
        "CUSZZ",
        "s76",
        "@UNKNOWN_BLUE#0",
        [
          "mercy"
        ]
      ],
      [
        272069,
        0,
        "genji",
        "MINIMAL",
        "ana",
        "XXGROUPXXTH9",
        [
          "mercy"
        ]
      ],
      [
        278584,
        1,
        "dva",
        "SOONO3O4",
        "mccree",
        "THESHADOWXIV",
        [
        ]
      ],
      [
        280589,
        0,
        "genji",
        "MINIMAL",
        "winston",
        "BOOMBAT",
        [
          "mercy"
        ]
      ],
      [
        280589,
        1,
        "genji",
        "SENSOR",
        "mercy",
        "FROSTYFEET",
        [
        ]
      ],
      [
        281591,
        0,
        "lucio",
        "KONGLAZY",
        "genji",
        "SENSOR",
        [
        ]
      ],
      [
        288106,
        1,
        "dva",
        "SOONO3O4",
        "reaper",
        "SAVAGEWOLFIE",
        [
        ]
      ],
      [
        306645,
        2,
        "mercy",
        "FROSTYFEET",
        "genji",
        "MINIMAL",
        [
        ]
      ],
      [
        308651,
        1,
        null,
        null,
        "genji",
        "MINIMAL",
        [
        ]
      ],
      [
        312659,
        0,
        "genji",
        "MINIMAL",
        "ana",
        "XXGROUPXXTH9",
        [
        ]
      ],
      [
        320174,
        0,
        "lucio",
        "KONGLAZY",
        "s76",
        "@UNKNOWN_BLUE#0",
        [
          "mercy",
          "mccree"
        ]
      ],
      [
        321176,
        0,
        "reaper",
        "SAVAGEWOLFIE",
        "lucio",
        "NOTROB",
        [
        ]
      ],
      [
        322178,
        0,
        "roadhog",
        "CUSZZ",
        "dva_mech",
        "SOONO3O4",
        [
        ]
      ],
      [
        326186,
        0,
        "roadhog",
        "CUSZZ",
        "dva",
        "SOONO3O4",
        [
          "mercy"
        ]
      ],
      [
        328192,
        0,
        "mccree",
        "THESHADOWXIV",
        "winston",
        "BOOMBAT",
        [
          "mercy"
        ]
      ],
      [
        329194,
        0,
        "genji",
        "MINIMAL",
        "genji",
        "SENSOR",
        [
        ]
      ],
      [
        395334,
        0,
        "mccree",
        "THESHADOWXIV",
        "pharah",
        "@UNKNOWN_BLUE#0",
        [
          "mercy"
        ]
      ],
      [
        395835,
        0,
        "roadhog",
        "CUSZZ",
        "lucio",
        "NOTROB",
        [
        ]
      ],
      [
        397339,
        1,
        "hanzo",
        "SENSOR",
        "lucio",
        "KONGLAZY",
        [
        ]
      ],
      [
        403349,
        0,
        "genji",
        "MINIMAL",
        "mercy",
        "XXGROUPXXTH9",
        [
        ]
      ],
      [
        404853,
        1,
        "winston",
        "BOOMBAT",
        "genji",
        "MINIMAL",
        [
        ]
      ],
      [
        404853,
        0,
        "mccree",
        "THESHADOWXIV",
        "hanzo",
        "SENSOR",
        [
        ]
      ],
      [
        407358,
        0,
        "reaper",
        "SAVAGEWOLFIE",
        "winston",
        "BOOMBAT",
        [
          "mccree",
          "mercy"
        ]
      ],
      [
        412369,
        0,
        "reaper",
        "SAVAGEWOLFIE",
        "dva_mech",
        "SOONO3O4",
        [
          "mercy"
        ]
      ],
      [
        416377,
        0,
        "roadhog",
        "CUSZZ",
        "dva",
        "SOONO3O4",
        [
          "mercy"
        ]
      ],
      [
        451957,
        1,
        "hanzo",
        "SENSOR",
        "roadhog",
        "CUSZZ",
        [
        ]
      ],
      [
        452959,
        1,
        null,
        null,
        "roadhog",
        "CUSZZ",
        [
        ]
      ],
      [
        453961,
        2,
        "mercy",
        "FROSTYFEET",
        "roadhog",
        "CUSZZ",
        [
        ]
      ],
      [
        454963,
        1,
        "hanzo",
        "SENSOR",
        "reaper",
        "SAVAGEWOLFIE",
        [
          "zenyatta"
        ]
      ],
      [
        457969,
        1,
        "zarya",
        "BOOMBAT",
        "genji",
        "MINIMAL",
        [
          "zenyatta"
        ]
      ],
      [
        463983,
        1,
        "zenyatta",
        "NOTROB",
        "mccree",
        "THESHADOWXIV",
        [
        ]
      ],
      [
        468492,
        1,
        "hanzo",
        "SENSOR",
        "lucio",
        "KONGLAZY",
        [
        ]
      ],
      [
        472000,
        1,
        "hanzo",
        "SENSOR",
        "mercy",
        "FROSTYFEET",
        [
          "mercy",
          "zenyatta"
        ]
      ],
      [
        475507,
        1,
        "hanzo",
        "SENSOR",
        "roadhog",
        "CUSZZ",
        [
          "mercy",
          "zenyatta"
        ]
      ],
      [
        489039,
        1,
        "dva",
        "SOONO3O4",
        "mccree",
        "THESHADOWXIV",
        [
        ]
      ],
      [
        490041,
        1,
        "hanzo",
        "SENSOR",
        "reaper",
        "SAVAGEWOLFIE",
        [
        ]
      ],
      [
        499060,
        0,
        "roadhog",
        "CUSZZ",
        "genji",
        "@UNKNOWN_BLUE#0",
        [
          "mercy"
        ]
      ],
      [
        500563,
        0,
        "genji",
        "MINIMAL",
        "hanzo",
        "SENSOR",
        [
        ]
      ],
      [
        511586,
        0,
        "genji",
        "MINIMAL",
        "mercy",
        "XXGROUPXXTH9",
        [
        ]
      ],
      [
        517599,
        0,
        "roadhog",
        "CUSZZ",
        "zarya",
        "BOOMBAT",
        [
        ]
      ],
      [
        526113,
        0,
        "reaper",
        "SAVAGEWOLFIE",
        "genji",
        "@UNKNOWN_BLUE#0",
        [
          "mercy",
          "roadhog"
        ]
      ],
      [
        528118,
        0,
        "mccree",
        "THESHADOWXIV",
        "zenyatta",
        "NOTROB",
        [
        ]
      ],
      [
        532627,
        0,
        "mccree",
        "THESHADOWXIV",
        "dva",
        "SOONO3O4",
        [
        ]
      ],
      [
        533629,
        0,
        "reaper",
        "SAVAGEWOLFIE",
        "mercy",
        "XXGROUPXXTH9",
        [
          "mercy",
          "mccree"
        ]
      ],
      [
        568198,
        1,
        "zenyatta",
        "NOTROB",
        "genji",
        "MINIMAL",
        [
        ]
      ],
      [
        569702,
        0,
        "mccree",
        "THESHADOWXIV",
        "mercy",
        "XXGROUPXXTH9",
        [
        ]
      ],
      [
        571706,
        1,
        null,
        null,
        "genji",
        "MINIMAL",
        [
        ]
      ],
      [
        572207,
        2,
        "mercy",
        "FROSTYFEET",
        "genji",
        "MINIMAL",
        [
        ]
      ],
      [
        577218,
        0,
        "mccree",
        "THESHADOWXIV",
        "hanzo",
        "SENSOR",
        [
        ]
      ],
      [
        578221,
        1,
        "zenyatta",
        "NOTROB",
        "mccree",
        "THESHADOWXIV",
        [
        ]
      ],
      [
        580726,
        0,
        "roadhog",
        "CUSZZ",
        "zenyatta",
        "NOTROB",
        [
        ]
      ],
      [
        585236,
        0,
        "roadhog",
        "CUSZZ",
        "dva_mech",
        "SOONO3O4",
        [
        ]
      ],
      [
        585236,
        0,
        "lucio",
        "KONGLAZY",
        "zarya",
        "BOOMBAT",
        [
          "mercy"
        ]
      ],
      [
        589245,
        0,
        "genji",
        "MINIMAL",
        "dva",
        "SOONO3O4",
        [
        ]
      ],
      [
        594254,
        0,
        "genji",
        "MINIMAL",
        "genji",
        "@UNKNOWN_BLUE#0",
        [
          "mercy"
        ]
      ],
      [
        595757,
        3,
        "mercy",
        "XXGROUPXXTH9",
        "dva",
        "SOONO3O4",
        [
        ]
      ],
      [
        599766,
        0,
        "genji",
        "MINIMAL",
        "mercy",
        "XXGROUPXXTH9",
        [
          "mercy"
        ]
      ],
      [
        611290,
        0,
        "reaper",
        "SAVAGEWOLFIE",
        "hanzo",
        "SENSOR",
        [
          "mercy"
        ]
      ],
      [
        612292,
        1,
        "dva",
        "SOONO3O4",
        "mercy",
        "FROSTYFEET",
        [
        ]
      ],
      [
        619809,
        1,
        "zenyatta",
        "NOTROB",
        "reaper",
        "SAVAGEWOLFIE",
        [
        ]
      ],
      [
        623816,
        0,
        "mccree",
        "THESHADOWXIV",
        "genji",
        "@UNKNOWN_BLUE#0",
        [
          "roadhog"
        ]
      ],
      [
        625820,
        1,
        "zarya",
        "BOOMBAT",
        "lucio",
        "KONGLAZY",
        [
          "zenyatta"
        ]
      ],
      [
        626321,
        1,
        "dva",
        "SOONO3O4",
        "roadhog",
        "CUSZZ",
        [
          "zarya",
          "zenyatta"
        ]
      ],
      [
        642856,
        0,
        "genji",
        "MINIMAL",
        "zenyatta",
        "NOTROB",
        [
          "mercy"
        ]
      ],
      [
        654880,
        0,
        "reaper",
        "SAVAGEWOLFIE",
        "hanzo",
        "SENSOR",
        [
        ]
      ],
      [
        656884,
        0,
        "reaper",
        "SAVAGEWOLFIE",
        "zarya",
        "BOOMBAT",
        [
        ]
      ],
      [
        658388,
        0,
        "reaper",
        "SAVAGEWOLFIE",
        "mercy",
        "XXGROUPXXTH9",
        [
          "mercy"
        ]
      ],
      [
        661394,
        0,
        "reaper",
        "SAVAGEWOLFIE",
        "dva_mech",
        "SOONO3O4",
        [
          "mercy"
        ]
      ],
      [
        662396,
        0,
        "mccree",
        "THESHADOWXIV",
        "genji",
        "@UNKNOWN_BLUE#0",
        [
        ]
      ],
      [
        662396,
        0,
        "genji",
        "MINIMAL",
        "dva",
        "SOONO3O4",
        [
        ]
      ],
      [
        669909,
        1,
        "zenyatta",
        "NOTROB",
        "genji",
        "MINIMAL",
        [
        ]
      ],
      [
        738559,
        1,
        "hanzo",
        "SENSOR",
        "mccree",
        "THESHADOWXIV",
        [
        ]
      ],
      [
        747579,
        1,
        "hanzo",
        "SENSOR",
        "genji",
        "MINIMAL",
        [
        ]
      ],
      [
        753091,
        1,
        "roadhog",
        "XXGROUPXXTH9",
        "pharah",
        "SAVAGEWOLFIE",
        [
        ]
      ],
      [
        756599,
        1,
        "hanzo",
        "SENSOR",
        "lucio",
        "KONGLAZY",
        [
        ]
      ],
      [
        764117,
        1,
        "roadhog",
        "XXGROUPXXTH9",
        "mccree",
        "THESHADOWXIV",
        [
        ]
      ],
      [
        790677,
        1,
        "hanzo",
        "SENSOR",
        "reaper",
        "SAVAGEWOLFIE",
        [
        ]
      ],
      [
        790677,
        0,
        "genji",
        "MINIMAL",
        "hanzo",
        "SENSOR",
        [
          "mercy"
        ]
      ],
      [
        793684,
        0,
        "genji",
        "MINIMAL",
        "mercy",
        "NOTROB",
        [
          "mercy"
        ]
      ],
      [
        794686,
        1,
        "tracer",
        "SOONO3O4",
        "mccree",
        "THESHADOWXIV",
        [
        ]
      ],
      [
        801198,
        0,
        "genji",
        "MINIMAL",
        "junkrat",
        "BOOMBAT",
        [
          "mercy"
        ]
      ],
      [
        802201,
        0,
        "genji",
        "MINIMAL",
        "tracer",
        "SOONO3O4",
        [
        ]
      ],
      [
        809717,
        1,
        "roadhog",
        "XXGROUPXXTH9",
        "mercy",
        "FROSTYFEET",
        [
        ]
      ],
      [
        837776,
        0,
        "genji",
        "MINIMAL",
        "tracer",
        "SOONO3O4",
        [
        ]
      ],
      [
        838778,
        1,
        "roadhog",
        "XXGROUPXXTH9",
        "roadhog",
        "THESHADOWXIV",
        [
        ]
      ],
      [
        839780,
        0,
        "genji",
        "MINIMAL",
        "junkrat",
        "BOOMBAT",
        [
        ]
      ],
      [
        840783,
        0,
        "genji",
        "MINIMAL",
        "hanzo",
        "SENSOR",
        [
        ]
      ],
      [
        843790,
        3,
        "mercy",
        "NOTROB",
        "hanzo",
        "SENSOR",
        [
        ]
      ],
      [
        843790,
        3,
        "mercy",
        "NOTROB",
        "tracer",
        "SOONO3O4",
        [
        ]
      ],
      [
        844291,
        1,
        "roadhog",
        "XXGROUPXXTH9",
        "genji",
        "MINIMAL",
        [
        ]
      ],
      [
        844291,
        2,
        "mercy",
        "FROSTYFEET",
        "roadhog",
        "THESHADOWXIV",
        [
        ]
      ],
      [
        846797,
        1,
        null,
        null,
        "roadhog",
        "THESHADOWXIV",
        [
        ]
      ],
      [
        849803,
        1,
        "hanzo",
        "SENSOR",
        "lucio",
        "KONGLAZY",
        [
          "mercy"
        ]
      ],
      [
        854313,
        0,
        "reaper",
        "SAVAGEWOLFIE",
        "hanzo",
        "SENSOR",
        [
        ]
      ],
      [
        859323,
        0,
        "reaper",
        "SAVAGEWOLFIE",
        "mercy",
        "NOTROB",
        [
        ]
      ],
      [
        864334,
        1,
        "roadhog",
        "XXGROUPXXTH9",
        "reaper",
        "SAVAGEWOLFIE",
        [
        ]
      ],
      [
        867340,
        0,
        "roadhog",
        "THESHADOWXIV",
        "roadhog",
        "XXGROUPXXTH9",
        [
          "mercy"
        ]
      ],
      [
        872350,
        0,
        "lucio",
        "KONGLAZY",
        "winston",
        "@UNKNOWN_BLUE#0",
        [
        ]
      ],
      [
        878866,
        0,
        "genji",
        "MINIMAL",
        "junkrat",
        "BOOMBAT",
        [
        ]
      ],
      [
        881372,
        0,
        "roadhog",
        "THESHADOWXIV",
        "tracer",
        "SOONO3O4",
        [
        ]
      ],
      [
        886383,
        0,
        "genji",
        "MINIMAL",
        "mercy",
        "NOTROB",
        [
        ]
      ],
      [
        893897,
        0,
        "lucio",
        "KONGLAZY",
        "hanzo",
        "SENSOR",
        [
          "mercy"
        ]
      ],
      [
        909930,
        0,
        "reaper",
        "SAVAGEWOLFIE",
        "winston",
        "@UNKNOWN_BLUE#0",
        [
          "mercy"
        ]
      ],
      [
        911935,
        0,
        "roadhog",
        "THESHADOWXIV",
        "junkrat",
        "BOOMBAT",
        [
        ]
      ],
      [
        913939,
        1,
        "roadhog",
        "XXGROUPXXTH9",
        "roadhog",
        "THESHADOWXIV",
        [
        ]
      ],
      [
        914441,
        1,
        "tracer",
        "SOONO3O4",
        "reaper",
        "SAVAGEWOLFIE",
        [
        ]
      ],
      [
        914942,
        1,
        null,
        null,
        "roadhog",
        "THESHADOWXIV",
        [
        ]
      ],
      [
        914942,
        1,
        null,
        null,
        "reaper",
        "SAVAGEWOLFIE",
        [
        ]
      ],
      [
        915443,
        2,
        "mercy",
        "FROSTYFEET",
        "roadhog",
        "THESHADOWXIV",
        [
        ]
      ],
      [
        915443,
        2,
        "mercy",
        "FROSTYFEET",
        "reaper",
        "SAVAGEWOLFIE",
        [
        ]
      ],
      [
        919453,
        0,
        "reaper",
        "SAVAGEWOLFIE",
        "roadhog",
        "XXGROUPXXTH9",
        [
          "mercy"
        ]
      ],
      [
        919453,
        3,
        "mercy",
        "NOTROB",
        "roadhog",
        "XXGROUPXXTH9",
        [
        ]
      ],
      [
        919453,
        3,
        "mercy",
        "NOTROB",
        "junkrat",
        "BOOMBAT",
        [
        ]
      ],
      [
        922459,
        0,
        "reaper",
        "SAVAGEWOLFIE",
        "mercy",
        "NOTROB",
        [
        ]
      ],
      [
        923962,
        1,
        "roadhog",
        "XXGROUPXXTH9",
        "reaper",
        "SAVAGEWOLFIE",
        [
          "mercy"
        ]
      ],
      [
        923962,
        0,
        "roadhog",
        "THESHADOWXIV",
        "roadhog",
        "XXGROUPXXTH9",
        [
          "mercy"
        ]
      ],
      [
        924965,
        1,
        "junkrat",
        "BOOMBAT",
        "lucio",
        "KONGLAZY",
        [
        ]
      ],
      [
        931479,
        0,
        "roadhog",
        "THESHADOWXIV",
        "junkrat",
        "BOOMBAT",
        [
        ]
      ],
      [
        940998,
        0,
        "roadhog",
        "THESHADOWXIV",
        "hanzo",
        "SENSOR",
        [
          "mercy"
        ]
      ],
      [
        945509,
        0,
        "roadhog",
        "THESHADOWXIV",
        "dva_mech",
        "@UNKNOWN_BLUE#0",
        [
          "mercy"
        ]
      ],
      [
        946009,
        0,
        "roadhog",
        "THESHADOWXIV",
        "dva",
        "@UNKNOWN_BLUE#0",
        [
          "mercy"
        ]
      ],
      [
        949517,
        0,
        "genji",
        "MINIMAL",
        "tracer",
        "SOONO3O4",
        [
          "mercy"
        ]
      ],
      [
        956030,
        0,
        "reaper",
        "SAVAGEWOLFIE",
        "roadhog",
        "XXGROUPXXTH9",
        [
          "mercy"
        ]
      ],
      [
        978580,
        0,
        "reaper",
        "SAVAGEWOLFIE",
        "pharah",
        "BOOMBAT",
        [
        ]
      ],
      [
        984594,
        1,
        "roadhog",
        "XXGROUPXXTH9",
        "reaper",
        "SAVAGEWOLFIE",
        [
        ]
      ],
      [
        986598,
        2,
        "mercy",
        "FROSTYFEET",
        "reaper",
        "SAVAGEWOLFIE",
        [
        ]
      ],
      [
        992107,
        1,
        "hanzo",
        "SENSOR",
        "mercy",
        "FROSTYFEET",
        [
          "mercy"
        ]
      ],
      [
        997619,
        0,
        "reaper",
        "SAVAGEWOLFIE",
        "hanzo",
        "SENSOR",
        [
        ]
      ],
      [
        999621,
        0,
        "genji",
        "MINIMAL",
        "mercy",
        "NOTROB",
        [
        ]
      ],
      [
        1000623,
        0,
        "reaper",
        "SAVAGEWOLFIE",
        "roadhog",
        "XXGROUPXXTH9",
        [
        ]
      ],
      [
        1011145,
        0,
        "genji",
        "MINIMAL",
        "reinhardt",
        "BOOMBAT",
        [
        ]
      ],
      [
        1014151,
        0,
        "lucio",
        "KONGLAZY",
        "tracer",
        "SOONO3O4",
        [
        ]
      ]
    ],
    "map": "Oasis",
    "map_type": "Control",
    "objective_stages": [
      {
        "end": 320174,
        "end_score": [
          0,
          1
        ],
        "ownership": [
          {
            "end": 174865,
            "owner": "blue",
            "start": 104715
          },
          {
            "end": 318170,
            "owner": "red",
            "start": 174865
          }
        ],
        "stage": "City Center (A)",
        "start": 22540
      },
      {
        "end": 670410,
        "end_score": [
          0,
          2
        ],
        "ownership": [
          {
            "end": 472501,
            "owner": "red",
            "start": 414373
          },
          {
            "end": 528118,
            "owner": "blue",
            "start": 472501
          },
          {
            "end": 627824,
            "owner": "red",
            "start": 528118
          },
          {
            "end": 666404,
            "owner": "blue",
            "start": 627824
          },
          {
            "end": 668407,
            "owner": "red",
            "start": 666404
          }
        ],
        "stage": "Gardens (C)",
        "start": 338711
      },
      {
        "end": 1036196,
        "end_score": [
          0,
          3
        ],
        "ownership": [
          {
            "end": 883877,
            "owner": "blue",
            "start": 752590
          },
          {
            "end": 1018660,
            "owner": "red",
            "start": 883877
          }
        ],
        "stage": "University (B)",
        "start": 690454
      }
    ],
    "owner": "notrob#1514",
    "player": "NOTROB",
    "result": "LOSS",
    "score": [
      0,
      3
    ],
    "start_sr": 2622,
    "tab_statistics": {
      "damage": [
        0,
        0,
        0,
        0,
        0,
        921,
        921,
        921,
        1111,
        1111,
        1711,
        1711,
        1711,
        2376,
        2376,
        2376,
        2376,
        2376,
        2401,
        2401,
        2401,
        2401,
        3607,
        3607,
        3607,
        4205,
        4205,
        4205,
        4205,
        4939,
        4939,
        4939,
        4939,
        5139,
        5139,
        5139,
        5139,
        5139,
        5139,
        5139,
        5139,
        5139,
        5139,
        5139,
        5179,
        5179,
        5179,
        5179,
        5179,
        5179,
        5179,
        5179,
        5179,
        5179,
        5179,
        5179,
        5179,
        5179
      ],
      "deaths": [
        0,
        0,
        0,
        0,
        0,
        1,
        1,
        1,
        2,
        2,
        3,
        3,
        3,
        4,
        4,
        4,
        4,
        4,
        5,
        5,
        5,
        5,
        6,
        6,
        6,
        7,
        7,
        7,
        7,
        8,
        8,
        8,
        8,
        8,
        8,
        8,
        8,
        8,
        8,
        8,
        9,
        9,
        9,
        9,
        10,
        10,
        10,
        11,
        11,
        11,
        12,
        12,
        12,
        12,
        13,
        13,
        13,
        13
      ],
      "elims": [
        0,
        0,
        0,
        0,
        0,
        3,
        3,
        3,
        3,
        3,
        3,
        3,
        3,
        4,
        4,
        4,
        4,
        4,
        4,
        4,
        4,
        4,
        8,
        8,
        8,
        10,
        10,
        10,
        10,
        13,
        13,
        13,
        13,
        14,
        14,
        14,
        14,
        14,
        14,
        14,
        14,
        14,
        14,
        14,
        14,
        14,
        14,
        14,
        14,
        14,
        14,
        14,
        14,
        14,
        14,
        14,
        14,
        14
      ],
      "healing": [
        0,
        0,
        0,
        0,
        0,
        676,
        676,
        676,
        676,
        676,
        976,
        976,
        976,
        1916,
        1916,
        1916,
        1916,
        1916,
        1990,
        1990,
        1990,
        1990,
        3479,
        3479,
        3479,
        4014,
        4014,
        4014,
        4014,
        4482,
        4482,
        4482,
        4482,
        4482,
        4482,
        4482,
        4482,
        4482,
        4482,
        5612,
        6180,
        6180,
        6180,
        6331,
        8197,
        8197,
        8197,
        8334,
        8334,
        8334,
        8843,
        8843,
        8843,
        8843,
        10146,
        10146,
        10146,
        10146
      ],
      "hero": [
        "lucio",
        "lucio",
        "lucio",
        "lucio",
        "lucio",
        "lucio",
        "lucio",
        "lucio",
        "lucio",
        "lucio",
        "lucio",
        "lucio",
        "lucio",
        "lucio",
        "lucio",
        "lucio",
        "lucio",
        "lucio",
        "lucio",
        "lucio",
        "zenyatta",
        "zenyatta",
        "zenyatta",
        "zenyatta",
        "zenyatta",
        "zenyatta",
        "zenyatta",
        "zenyatta",
        "zenyatta",
        "zenyatta",
        "zenyatta",
        "zenyatta",
        "zenyatta",
        "zenyatta",
        "zenyatta",
        "zenyatta",
        "zenyatta",
        "mercy",
        "mercy",
        "mercy",
        "mercy",
        "mercy",
        "mercy",
        "mercy",
        "mercy",
        "mercy",
        "mercy",
        "mercy",
        "mercy",
        "mercy",
        "mercy",
        "mercy",
        "mercy",
        "mercy",
        "mercy",
        "mercy",
        "mercy",
        "mercy"
      ],
      "hero_stat_1": [
        0,
        0,
        0,
        0,
        0,
        43,
        43,
        43,
        43,
        43,
        32,
        32,
        32,
        27,
        27,
        27,
        27,
        27,
        26,
        26,
        0,
        0,
        17,
        17,
        17,
        20,
        20,
        20,
        20,
        21,
        21,
        21,
        21,
        22,
        22,
        22,
        22,
        0,
        0,
        0,
        0,
        0,
        0,
        0,
        1,
        1,
        1,
        1,
        1,
        1,
        2,
        2,
        2,
        2,
        3,
        3,
        3,
        3
      ],
      "hero_stat_2": [
        0,
        0,
        0,
        0,
        0,
        2,
        2,
        2,
        2,
        2,
        2,
        2,
        2,
        2,
        2,
        2,
        2,
        2,
        2,
        2,
        0,
        0,
        3,
        3,
        3,
        3,
        3,
        3,
        3,
        8,
        8,
        8,
        8,
        8,
        8,
        8,
        8,
        0,
        0,
        0,
        0,
        0,
        0,
        0,
        0,
        0,
        0,
        0,
        0,
        0,
        0,
        0,
        0,
        0,
        0,
        0,
        0,
        0
      ],
      "hero_stat_3": [
        0,
        0,
        0,
        0,
        0,
        3,
        3,
        3,
        3,
        3,
        3,
        3,
        3,
        3,
        3,
        3,
        3,
        3,
        3,
        3,
        0,
        0,
        4,
        4,
        4,
        4,
        4,
        4,
        4,
        4,
        4,
        4,
        4,
        4,
        4,
        4,
        4,
        0,
        0,
        3,
        3,
        3,
        3,
        3,
        4,
        5,
        5,
        5,
        5,
        5,
        8,
        8,
        8,
        8,
        9,
        9,
        9,
        9
      ],
      "hero_stat_4": [
        0,
        0,
        0,
        0,
        0,
        2,
        2,
        2,
        2,
        2,
        2,
        2,
        2,
        2,
        2,
        2,
        2,
        2,
        2,
        2,
        0,
        0,
        95,
        95,
        95,
        174,
        174,
        174,
        174,
        174,
        174,
        174,
        174,
        174,
        174,
        174,
        174,
        0,
        0,
        36,
        56,
        56,
        56,
        56,
        67,
        67,
        67,
        104,
        104,
        104,
        104,
        104,
        104,
        104,
        104,
        104,
        104,
        104
      ],
      "hero_stat_5": [
        0,
        0,
        0,
        0,
        0,
        0,
        0,
        0,
        0,
        0,
        5,
        5,
        5,
        5,
        5,
        5,
        5,
        5,
        5,
        5,
        0,
        0,
        5,
        5,
        5,
        5,
        5,
        5,
        5,
        9,
        9,
        9,
        9,
        9,
        9,
        9,
        9,
        0,
        0,
        0,
        0,
        0,
        0,
        0,
        2,
        2,
        2,
        2,
        2,
        2,
        4,
        4,
        4,
        4,
        4,
        4,
        4,
        4
      ],
      "hero_stat_6": [
        null,
        null,
        null,
        null,
        null,
        null,
        null,
        null,
        null,
        null,
        null,
        null,
        null,
        null,
        null,
        null,
        null,
        null,
        null,
        null,
        null,
        null,
        null,
        null,
        null,
        null,
        null,
        null,
        null,
        null,
        null,
        null,
        null,
        null,
        null,
        null,
        null,
        null,
        null,
        null,
        null,
        null,
        null,
        null,
        null,
        null,
        null,
        null,
        null,
        null,
        null,
        null,
        null,
        null,
        null,
        null,
        null,
        null
      ],
      "objective_kills": [
        0,
        0,
        0,
        0,
        0,
        0,
        0,
        0,
        0,
        0,
        0,
        0,
        0,
        1,
        1,
        1,
        1,
        1,
        1,
        1,
        1,
        1,
        2,
        2,
        2,
        3,
        3,
        3,
        3,
        5,
        5,
        5,
        5,
        6,
        6,
        6,
        6,
        6,
        6,
        6,
        6,
        6,
        6,
        6,
        6,
        6,
        6,
        6,
        6,
        6,
        6,
        6,
        6,
        6,
        6,
        6,
        6,
        6
      ],
      "objective_time": [
        0,
        0,
        0,
        0,
        0,
        7,
        7,
        7,
        9,
        9,
        19,
        19,
        19,
        62,
        62,
        62,
        62,
        62,
        62,
        62,
        62,
        62,
        64,
        64,
        64,
        70,
        70,
        70,
        70,
        79,
        79,
        79,
        79,
        79,
        79,
        79,
        79,
        79,
        79,
        82,
        85,
        85,
        85,
        85,
        96,
        96,
        96,
        96,
        96,
        96,
        96,
        96,
        96,
        96,
        106,
        106,
        106,
        106
      ],
      "time": [
        43084,
        49599,
        57615,
        63628,
        75153,
        125261,
        132276,
        140292,
        155825,
        160835,
        225976,
        230986,
        235997,
        321677,
        328192,
        333702,
        354744,
        363765,
        396337,
        401847,
        406857,
        411868,
        529120,
        534631,
        539641,
        581728,
        588744,
        594755,
        601268,
        643357,
        648868,
        654379,
        660392,
        675421,
        689451,
        694463,
        699974,
        716009,
        722523,
        771634,
        794184,
        801198,
        814729,
        820239,
        860326,
        865836,
        871348,
        887384,
        892394,
        897905,
        923462,
        928973,
        933983,
        943002,
        1000123,
        1005633,
        1011647,
        1019662
      ]
    },
    "teams": {
      "blue": [
        {
          "heroes": [
            {
              "end": 395835,
              "hero": "lucio",
              "start": 98701
            },
            {
              "end": 669909,
              "hero": "zenyatta",
              "start": 463983
            },
            {
              "end": 1014151,
              "hero": "mercy",
              "start": 793684
            }
          ],
          "name": "NOTROB"
        },
        {
          "heroes": [
            {
              "end": 407358,
              "hero": "winston",
              "start": 94694
            },
            {
              "end": 656884,
              "hero": "zarya",
              "start": 457969
            },
            {
              "end": 931479,
              "hero": "junkrat",
              "start": 801198
            },
            {
              "end": 978580,
              "hero": "pharah",
              "start": 978580
            },
            {
              "end": 1014151,
              "hero": "reinhardt",
              "start": 1011145
            }
          ],
          "name": "BOOMBAT"
        },
        {
          "heroes": [
            {
              "end": 320174,
              "hero": "s76",
              "start": 137286
            },
            {
              "end": 395334,
              "hero": "pharah",
              "start": 395334
            },
            {
              "end": 662396,
              "hero": "genji",
              "start": 499060
            },
            {
              "end": 909930,
              "hero": "winston",
              "start": 872350
            },
            {
              "end": 1014151,
              "hero": "dva",
              "start": 946009
            }
          ],
          "name": "@UNKNOWN_BLUE#0"
        },
        {
          "heroes": [
            {
              "end": 329194,
              "hero": "genji",
              "start": 86175
            },
            {
              "end": 1014151,
              "hero": "hanzo",
              "start": 397339
            }
          ],
          "name": "SENSOR"
        },
        {
          "heroes": [
            {
              "end": 662396,
              "hero": "dva",
              "start": 126263
            },
            {
              "end": 1014151,
              "hero": "tracer",
              "start": 794686
            }
          ],
          "name": "SOONO3O4"
        },
        {
          "heroes": [
            {
              "end": 312659,
              "hero": "ana",
              "start": 149815
            },
            {
              "end": 658388,
              "hero": "mercy",
              "start": 403349
            },
            {
              "end": 1014151,
              "hero": "roadhog",
              "start": 753091
            }
          ],
          "name": "XXGROUPXXTH9"
        }
      ],
      "red": [
        {
          "heroes": [
            {
              "end": 1014151,
              "hero": "lucio",
              "start": 212447
            }
          ],
          "name": "KONGLAZY"
        },
        {
          "heroes": [
            {
              "end": 661394,
              "hero": "reaper",
              "start": 98701
            },
            {
              "end": 753091,
              "hero": "pharah",
              "start": 753091
            },
            {
              "end": 1014151,
              "hero": "reaper",
              "start": 790677
            }
          ],
          "name": "SAVAGEWOLFIE"
        },
        {
          "heroes": [
            {
              "end": 1014151,
              "hero": "mercy",
              "start": 94694
            }
          ],
          "name": "FROSTYFEET"
        },
        {
          "heroes": [
            {
              "end": 209940,
              "hero": "winston",
              "start": 86175
            },
            {
              "end": 794686,
              "hero": "mccree",
              "start": 278584
            },
            {
              "end": 1014151,
              "hero": "roadhog",
              "start": 838778
            }
          ],
          "name": "THESHADOWXIV"
        },
        {
          "heroes": [
            {
              "end": 1014151,
              "hero": "roadhog",
              "start": 137286
            }
          ],
          "name": "CUSZZ"
        },
        {
          "heroes": [
            {
              "end": 1014151,
              "hero": "genji",
              "start": 109726
            }
          ],
          "name": "MINIMAL"
        }
      ]
    },
    "user_id": 2235147
  },
  "meta": {
    "duration": 1018,
    "end_sr": 2605,
    "heroes_played": [
      [
        "lucio",
        0.41067437704467147
      ],
      [
        "mercy",
        0.30471150350988974
      ],
      [
        "zenyatta",
        0.2846141194454388
      ]
    ],
    "key": "notrob-1514/2017-06-16-12-50-kBYGWKWpbQqUmZUfjNWUXV",
    "map": "Oasis",
    "player_name": "NOTROB",
    "rank": null,
    "result": "LOSS",
    "score": [
      0,
      3
    ],
    "start_sr": 2622,
    "time": 1497616331,
    "url": "https://s3-us-west-2.amazonaws.com/overtrack-parsed-games/notrob-1514/2017-06-16-12-50-kBYGWKWpbQqUmZUfjNWUXV/game.json",
    "user_id": 2235147
  }
}